django_streaming_coordinator-0.1.1.dist-info/licenses/LICENSE
streaming/__init__.py
streaming/admin.py
streaming/apps.py
streaming/client.py
streaming/coordinator.py
streaming/models.py
streaming/server.py
streaming/tests.py
streaming/views.py
streaming/management/__init__.py
streaming/management/commands/__init__.py
streaming/management/commands/cleanup_old_tasks.py
streaming/management/commands/runserver_stream.py
streaming/migrations/__init__.py
django_streaming_coordinator-0.1.1.dist-info/METADATA
django_streaming_coordinator-0.1.1.dist-info/WHEEL
django_streaming_coordinator-0.1.1.dist-info/top_level.txt
django_streaming_coordinator-0.1.1.dist-info/RECORD
