Metadata-Version: 2.4
Name: django-streaming-coordinator
Version: 0.1.1
Summary: A Django-based system for managing long-running tasks with Server-Sent Events (SSE) streaming
Author-email: Justus Hämäläinen <justushamalainen@gmail.com>
License-Expression: MIT
Project-URL: Homepage, https://github.com/Technology-Company/django-streaming-coordinator
Project-URL: Repository, https://github.com/Technology-Company/django-streaming-coordinator
Project-URL: Documentation, https://github.com/Technology-Company/django-streaming-coordinator#readme
Project-URL: Issues, https://github.com/Technology-Company/django-streaming-coordinator/issues
Keywords: django,sse,server-sent-events,streaming,async,tasks,background-tasks
Classifier: Development Status :: 4 - Beta
Classifier: Framework :: Django
Classifier: Framework :: Django :: 5.2
Classifier: Intended Audience :: Developers
Classifier: Operating System :: OS Independent
Classifier: Programming Language :: Python :: 3
Classifier: Programming Language :: Python :: 3.11
Classifier: Programming Language :: Python :: 3.12
Classifier: Topic :: Internet :: WWW/HTTP
Classifier: Topic :: Software Development :: Libraries :: Python Modules
Requires-Python: >=3.11
License-File: LICENSE
Requires-Dist: django<6.0.0,>=5.2.7
Requires-Dist: asgineer<0.10.0,>=0.9.4
Requires-Dist: uvicorn<0.38.0,>=0.37.0
Requires-Dist: httpx<0.29.0,>=0.28.1
Dynamic: license-file
